llama_index/voice_agents/gemini_live/__init__.py
llama_index/voice_agents/gemini_live/audio_interface.py
llama_index/voice_agents/gemini_live/base.py
llama_index/voice_agents/gemini_live/events.py
llama_index/voice_agents/gemini_live/utils.py
llama_index_voice_agents_gemini_live-0.2.1.dist-info/METADATA
llama_index_voice_agents_gemini_live-0.2.1.dist-info/WHEEL
llama_index_voice_agents_gemini_live-0.2.1.dist-info/licenses/LICENSE
llama_index_voice_agents_gemini_live-0.2.1.dist-info/RECORD
